slinkedList/Test.py
slinkedList/__init__.py
slinkedList/acc_types.py
slinkedList/exceptions.py
slinkedList/sample.py
slinkedList/slinkedList.py
slinkedList-0.0.3.dist-info/LICENSE.txt
slinkedList-0.0.3.dist-info/METADATA
slinkedList-0.0.3.dist-info/WHEEL
slinkedList-0.0.3.dist-info/top_level.txt
slinkedList-0.0.3.dist-info/RECORD
