Metadata-Version: 2.1
Name: slinkedList
Version: 0.0.3
Summary: In this package we simplifying the linked list concepts with useful functions
Author: Sree Ramya Gudiwada
Author-email: <sreeramyagud@gmail.com>
Keywords: python,first package
Classifier: Development Status :: 3 - Alpha
Classifier: Intended Audience :: Education
Classifier: Programming Language :: Python :: 2
Classifier: Programming Language :: Python :: 3
Classifier: Operating System :: MacOS :: MacOS X
Classifier: Operating System :: Microsoft :: Windows
License-File: LICENSE.txt
